vedro_replay/__init__.py
vedro_replay/command.py
vedro_replay/exclude.py
vedro_replay/filtering.py
vedro_replay/generator.py
vedro_replay/parse_excludes.py
vedro_replay/parse_requests.py
vedro_replay/replay.py
vedro_replay/request.py
vedro_replay/response.py
vedro_replay/templates/config.py.j2
vedro_replay/templates/contexts.py.j2
vedro_replay/templates/helper_method.j2
vedro_replay/templates/helpers.py.j2
vedro_replay/templates/interfaces.py.j2
vedro_replay/templates/scenario.py.j2
vedro_replay/templates/vedro.cfg.py.j2
vedro_replay-1.2.1.dist-info/licenses/LICENSE
vedro_replay-1.2.1.dist-info/METADATA
vedro_replay-1.2.1.dist-info/WHEEL
vedro_replay-1.2.1.dist-info/entry_points.txt
vedro_replay-1.2.1.dist-info/top_level.txt
vedro_replay-1.2.1.dist-info/RECORD
