Metadata-Version: 2.4
Name: vedro-replay
Version: 1.2.1
Summary: vedro-replay package
Home-page: https://github.com/kvs8/vedro-replay
Author: Konstantin Shefer
Author-email: kostya.shefer.999@gmail.com
License: Apache-2.0
Classifier: License :: OSI Approved :: Apache Software License
Classifier: Programming Language :: Python :: 3.9
Classifier: Programming Language :: Python :: 3.10
Classifier: Programming Language :: Python :: 3.11
Requires-Python: >=3.8
License-File: LICENSE
Requires-Dist: jinja2<4.0.0,>=3.1.4
Requires-Dist: cabina<2.0.0,>=1.0.0
Requires-Dist: d42<3.0.0,>=2.0.3
Requires-Dist: vedro<2.0,>=1.12.2
Requires-Dist: vedro-valera-validator<2.0.0,>=1.2.0
Requires-Dist: requests-toolbelt<2.0.0,>=1.0.0
Requires-Dist: pyparsing<4.0.0,>=3.2.0
Requires-Dist: vedro-httpx<1.0.0,>=0.5.0
Dynamic: author
Dynamic: author-email
Dynamic: classifier
Dynamic: description
Dynamic: description-content-type
Dynamic: home-page
Dynamic: license
Dynamic: license-file
Dynamic: requires-dist
Dynamic: requires-python
Dynamic: summary
